{"owner":{"id":1447,"alias":null,"number":"66","name":"Khoni","parent":null},"counted":24,"type":{"name":"Parliamentary Proportional"},"items":[{"subjects":[{"id":0,"number":"17","name":"| Sakartvelo","color":"#c24d1b","votes":0,"percent":0.0},{"id":0,"number":"10","name":"| Georgian Labour Party","color":"#292727","votes":7,"percent":0.542},{"id":0,"number":"25","name":"| Gakharia for Georgia","color":"#98ccd2","votes":123,"percent":9.52},{"id":0,"number":"12","name":"| Our United Georgia","color":"#0e2a52","votes":0,"percent":0.0},{"id":0,"number":"20","name":"| Free Georgia","color":"#a90f49","votes":1,"percent":0.077},{"id":0,"number":"26","name":"| Left-Wing Alliance","color":"#92864b","votes":1,"percent":0.077},{"id":0,"number":"16","name":"| Change Georgia","color":"#b4ac45","votes":7,"percent":0.542},{"id":0,"number":"21","name":"| Tribune","color":"#f9395a","votes":0,"percent":0.0},{"id":0,"number":"23","name":"| Chven","color":"#47752b","votes":2,"percent":0.155},{"id":0,"number":"3","name":"| The Party of Georgian Unity and Development","color":"#86b5ba","votes":2,"percent":0.155},{"id":0,"number":"27","name":"| Unity of Georgian","color":"#065fc1","votes":4,"percent":0.31},{"id":0,"number":"41","name":"| Georgian Dream","color":"#14477e","votes":732,"percent":56.656},{"id":0,"number":"5","name":"| Unity-National Movement","color":"#e72727","votes":103,"percent":7.972},{"id":0,"number":"36","name":"| Girchi","color":"#386a29","votes":21,"percent":1.625},{"id":0,"number":"9","name":"| Strong Georgia - Lelo, For People, For Liberty!","color":"#d5c907","votes":93,"percent":7.198},{"id":0,"number":"6","name":"| European Democrats","color":"#bbabdc","votes":9,"percent":0.697},{"id":0,"number":"8","name":"| Alliance of Patriots of Georgia","color":"#5848d2","votes":29,"percent":2.245},{"id":0,"number":"4","name":"| Coalition for Changes Gvaramia Melia Girchi Droa","color":"#bcca7a","votes":158,"percent":12.229}],"alias":"00.66.01","number":"01","name":null,"canceled":false,"info":null,"protId":"708da1d6-6f89-476e-9ea0-5eb9776d7ef7"},{"subjects":[{"id":0,"number":"17","name":"| Sakartvelo","color":"#c24d1b","votes":0,"percent":0.0},{"id":0,"number":"10","name":"| Georgian Labour Party","color":"#292727","votes":4,"percent":0.357},{"id":0,"number":"25","name":"| Gakharia for Georgia","color":"#98ccd2","votes":90,"percent":8.036},{"id":0,"number":"12","name":"| Our United Georgia","color":"#0e2a52","votes":0,"percent":0.0},{"id":0,"number":"20","name":"| Free Georgia","color":"#a90f49","votes":2,"percent":0.179},{"id":0,"number":"26","name":"| Left-Wing Alliance","color":"#92864b","votes":0,"percent":0.0},{"id":0,"number":"16","name":"| Change Georgia","color":"#b4ac45","votes":5,"percent":0.446},{"id":0,"number":"21","name":"| Tribune","color":"#f9395a","votes":2,"percent":0.179},{"id":0,"number":"23","name":"| Chven","color":"#47752b","votes":0,"percent":0.0},{"id":0,"number":"3","name":"| The Party of Georgian Unity and Development","color":"#86b5ba","votes":2,"percent":0.179},{"id":0,"number":"27","name":"| Unity of Georgian","color":"#065fc1","votes":6,"percent":0.536},{"id":0,"number":"41","name":"| Georgian Dream","color":"#14477e","votes":653,"percent":58.304},{"id":0,"number":"5","name":"| Unity-National Movement","color":"#e72727","votes":92,"percent":8.214},{"id":0,"number":"36","name":"| Girchi","color":"#386a29","votes":19,"percent":1.696},{"id":0,"number":"9","name":"| Strong Georgia - Lelo, For People, For Liberty!","color":"#d5c907","votes":72,"percent":6.429},{"id":0,"number":"6","name":"| European Democrats","color":"#bbabdc","votes":6,"percent":0.536},{"id":0,"number":"8","name":"| Alliance of Patriots of Georgia","color":"#5848d2","votes":12,"percent":1.071},{"id":0,"number":"4","name":"| Coalition for Changes Gvaramia Melia Girchi Droa","color":"#bcca7a","votes":155,"percent":13.839}],"alias":"00.66.02","number":"02","name":null,"canceled":false,"info":null,"protId":"7ece4afc-1660-4be0-8155-75a1991c22a8"},{"subjects":[{"id":0,"number":"17","name":"| Sakartvelo","color":"#c24d1b","votes":1,"percent":0.071},{"id":0,"number":"10","name":"| Georgian Labour Party","color":"#292727","votes":5,"percent":0.357},{"id":0,"number":"25","name":"| Gakharia for Georgia","color":"#98ccd2","votes":70,"percent":4.993},{"id":0,"number":"12","name":"| Our United Georgia","color":"#0e2a52","votes":1,"percent":0.071},{"id":0,"number":"20","name":"| Free Georgia","color":"#a90f49","votes":2,"percent":0.143},{"id":0,"number":"26","name":"| Left-Wing Alliance","color":"#92864b","votes":4,"percent":0.285},{"id":0,"number":"16","name":"| Change Georgia","color":"#b4ac45","votes":2,"percent":0.143},{"id":0,"number":"21","name":"| Tribune","color":"#f9395a","votes":1,"percent":0.071},{"id":0,"number":"23","name":"| Chven","color":"#47752b","votes":1,"percent":0.071},{"id":0,"number":"3","name":"| The Party of Georgian Unity and Development","color":"#86b5ba","votes":2,"percent":0.143},{"id":0,"number":"27","name":"| Unity of Georgian","color":"#065fc1","votes":7,"percent":0.499},{"id":0,"number":"41","name":"| Georgian Dream","color":"#14477e","votes":900,"percent":64.194},{"id":0,"number":"5","name":"| Unity-National Movement","color":"#e72727","votes":129,"percent":9.201},{"id":0,"number":"36","name":"| Girchi","color":"#386a29","votes":17,"percent":1.213},{"id":0,"number":"9","name":"| Strong Georgia - Lelo, For People, For Liberty!","color":"#d5c907","votes":93,"percent":6.633},{"id":0,"number":"6","name":"| European Democrats","color":"#bbabdc","votes":6,"percent":0.428},{"id":0,"number":"8","name":"| Alliance of Patriots of Georgia","color":"#5848d2","votes":20,"percent":1.427},{"id":0,"number":"4","name":"| Coalition for Changes Gvaramia Melia Girchi Droa","color":"#bcca7a","votes":141,"percent":10.057}],"alias":"00.66.03","number":"03","name":null,"canceled":false,"info":null,"protId":"66741e50-65af-4dca-a083-4fc3d094a7d0"},{"subjects":[{"id":0,"number":"17","name":"| Sakartvelo","color":"#c24d1b","votes":0,"percent":0.0},{"id":0,"number":"10","name":"| Georgian Labour Party","color":"#292727","votes":1,"percent":0.119},{"id":0,"number":"25","name":"| Gakharia for Georgia","color":"#98ccd2","votes":61,"percent":7.245},{"id":0,"number":"12","name":"| Our United Georgia","color":"#0e2a52","votes":0,"percent":0.0},{"id":0,"number":"20","name":"| Free Georgia","color":"#a90f49","votes":0,"percent":0.0},{"id":0,"number":"26","name":"| Left-Wing Alliance","color":"#92864b","votes":0,"percent":0.0},{"id":0,"number":"16","name":"| Change Georgia","color":"#b4ac45","votes":1,"percent":0.119},{"id":0,"number":"21","name":"| Tribune","color":"#f9395a","votes":3,"percent":0.356},{"id":0,"number":"23","name":"| Chven","color":"#47752b","votes":0,"percent":0.0},{"id":0,"number":"3","name":"| The Party of Georgian Unity and Development","color":"#86b5ba","votes":0,"percent":0.0},{"id":0,"number":"27","name":"| Unity of Georgian","color":"#065fc1","votes":4,"percent":0.475},{"id":0,"number":"41","name":"| Georgian Dream","color":"#14477e","votes":444,"percent":52.732},{"id":0,"number":"5","name":"| Unity-National Movement","color":"#e72727","votes":75,"percent":8.907},{"id":0,"number":"36","name":"| Girchi","color":"#386a29","votes":10,"percent":1.188},{"id":0,"number":"9","name":"| Strong Georgia - Lelo, For People, For Liberty!","color":"#d5c907","votes":27,"percent":3.207},{"id":0,"number":"6","name":"| European Democrats","color":"#bbabdc","votes":3,"percent":0.356},{"id":0,"number":"8","name":"| Alliance of Patriots of Georgia","color":"#5848d2","votes":7,"percent":0.831},{"id":0,"number":"4","name":"| Coalition for Changes Gvaramia Melia Girchi Droa","color":"#bcca7a","votes":206,"percent":24.466}],"alias":"00.66.04","number":"04","name":null,"canceled":false,"info":null,"protId":"cee351bd-f0ab-4902-ae03-2e4b70b10b7e"},{"subjects":[{"id":0,"number":"17","name":"| Sakartvelo","color":"#c24d1b","votes":0,"percent":0.0},{"id":0,"number":"10","name":"| Georgian Labour Party","color":"#292727","votes":4,"percent":0.605},{"id":0,"number":"25","name":"| Gakharia for Georgia","color":"#98ccd2","votes":37,"percent":5.598},{"id":0,"number":"12","name":"| Our United Georgia","color":"#0e2a52","votes":0,"percent":0.0},{"id":0,"number":"20","name":"| Free Georgia","color":"#a90f49","votes":2,"percent":0.303},{"id":0,"number":"26","name":"| Left-Wing Alliance","color":"#92864b","votes":0,"percent":0.0},{"id":0,"number":"16","name":"| Change Georgia","color":"#b4ac45","votes":1,"percent":0.151},{"id":0,"number":"21","name":"| Tribune","color":"#f9395a","votes":0,"percent":0.0},{"id":0,"number":"23","name":"| Chven","color":"#47752b","votes":0,"percent":0.0},{"id":0,"number":"3","name":"| The Party of Georgian Unity and Development","color":"#86b5ba","votes":3,"percent":0.454},{"id":0,"number":"27","name":"| Unity of Georgian","color":"#065fc1","votes":1,"percent":0.151},{"id":0,"number":"41","name":"| Georgian Dream","color":"#14477e","votes":382,"percent":57.791},{"id":0,"number":"5","name":"| Unity-National Movement","color":"#e72727","votes":85,"percent":12.859},{"id":0,"number":"36","name":"| Girchi","color":"#386a29","votes":15,"percent":2.269},{"id":0,"number":"9","name":"| Strong Georgia - Lelo, For People, For Liberty!","color":"#d5c907","votes":48,"percent":7.262},{"id":0,"number":"6","name":"| European Democrats","color":"#bbabdc","votes":7,"percent":1.059},{"id":0,"number":"8","name":"| Alliance of Patriots of Georgia","color":"#5848d2","votes":8,"percent":1.21},{"id":0,"number":"4","name":"| Coalition for Changes Gvaramia Melia Girchi Droa","color":"#bcca7a","votes":68,"percent":10.287}],"alias":"00.66.05","number":"05","name":null,"canceled":false,"info":null,"protId":"25f20d4c-78b9-4ca2-9d61-c9eacd54815f"},{"subjects":[{"id":0,"number":"17","name":"| Sakartvelo","color":"#c24d1b","votes":0,"percent":0.0},{"id":0,"number":"10","name":"| Georgian Labour Party","color":"#292727","votes":1,"percent":0.256},{"id":0,"number":"25","name":"| Gakharia for Georgia","color":"#98ccd2","votes":18,"percent":4.615},{"id":0,"number":"12","name":"| Our United Georgia","color":"#0e2a52","votes":2,"percent":0.513},{"id":0,"number":"20","name":"| Free Georgia","color":"#a90f49","votes":0,"percent":0.0},{"id":0,"number":"26","name":"| Left-Wing Alliance","color":"#92864b","votes":1,"percent":0.256},{"id":0,"number":"16","name":"| Change Georgia","color":"#b4ac45","votes":4,"percent":1.026},{"id":0,"number":"21","name":"| Tribune","color":"#f9395a","votes":2,"percent":0.513},{"id":0,"number":"23","name":"| Chven","color":"#47752b","votes":0,"percent":0.0},{"id":0,"number":"3","name":"| The Party of Georgian Unity and Development","color":"#86b5ba","votes":1,"percent":0.256},{"id":0,"number":"27","name":"| Unity of Georgian","color":"#065fc1","votes":3,"percent":0.769},{"id":0,"number":"41","name":"| Georgian Dream","color":"#14477e","votes":179,"percent":45.897},{"id":0,"number":"5","name":"| Unity-National Movement","color":"#e72727","votes":86,"percent":22.051},{"id":0,"number":"36","name":"| Girchi","color":"#386a29","votes":3,"percent":0.769},{"id":0,"number":"9","name":"| Strong Georgia - Lelo, For People, For Liberty!","color":"#d5c907","votes":39,"percent":10.0},{"id":0,"number":"6","name":"| European Democrats","color":"#bbabdc","votes":1,"percent":0.256},{"id":0,"number":"8","name":"| Alliance of Patriots of Georgia","color":"#5848d2","votes":16,"percent":4.103},{"id":0,"number":"4","name":"| Coalition for Changes Gvaramia Melia Girchi Droa","color":"#bcca7a","votes":34,"percent":8.718}],"alias":"00.66.06","number":"06","name":null,"canceled":false,"info":null,"protId":"60884650-cebb-4485-bf09-1a6d7f614a9f"},{"subjects":[{"id":0,"number":"17","name":"| Sakartvelo","color":"#c24d1b","votes":4,"percent":0.421},{"id":0,"number":"10","name":"| Georgian Labour Party","color":"#292727","votes":1,"percent":0.105},{"id":0,"number":"25","name":"| Gakharia for Georgia","color":"#98ccd2","votes":38,"percent":4.0},{"id":0,"number":"12","name":"| Our United Georgia","color":"#0e2a52","votes":1,"percent":0.105},{"id":0,"number":"20","name":"| Free Georgia","color":"#a90f49","votes":0,"percent":0.0},{"id":0,"number":"26","name":"| Left-Wing Alliance","color":"#92864b","votes":2,"percent":0.211},{"id":0,"number":"16","name":"| Change Georgia","color":"#b4ac45","votes":3,"percent":0.316},{"id":0,"number":"21","name":"| Tribune","color":"#f9395a","votes":4,"percent":0.421},{"id":0,"number":"23","name":"| Chven","color":"#47752b","votes":1,"percent":0.105},{"id":0,"number":"3","name":"| The Party of Georgian Unity and Development","color":"#86b5ba","votes":1,"percent":0.105},{"id":0,"number":"27","name":"| Unity of Georgian","color":"#065fc1","votes":2,"percent":0.211},{"id":0,"number":"41","name":"| Georgian Dream","color":"#14477e","votes":500,"percent":52.632},{"id":0,"number":"5","name":"| Unity-National Movement","color":"#e72727","votes":140,"percent":14.737},{"id":0,"number":"36","name":"| Girchi","color":"#386a29","votes":9,"percent":0.947},{"id":0,"number":"9","name":"| Strong Georgia - Lelo, For People, For Liberty!","color":"#d5c907","votes":59,"percent":6.211},{"id":0,"number":"6","name":"| European Democrats","color":"#bbabdc","votes":6,"percent":0.632},{"id":0,"number":"8","name":"| Alliance of Patriots of Georgia","color":"#5848d2","votes":23,"percent":2.421},{"id":0,"number":"4","name":"| Coalition for Changes Gvaramia Melia Girchi Droa","color":"#bcca7a","votes":156,"percent":16.421}],"alias":"00.66.07","number":"07","name":null,"canceled":false,"info":null,"protId":"17d7e528-d3e8-42a8-a273-ec92d973623d"},{"subjects":[{"id":0,"number":"17","name":"| Sakartvelo","color":"#c24d1b","votes":0,"percent":0.0},{"id":0,"number":"10","name":"| Georgian Labour Party","color":"#292727","votes":2,"percent":0.465},{"id":0,"number":"25","name":"| Gakharia for Georgia","color":"#98ccd2","votes":20,"percent":4.651},{"id":0,"number":"12","name":"| Our United Georgia","color":"#0e2a52","votes":0,"percent":0.0},{"id":0,"number":"20","name":"| Free Georgia","color":"#a90f49","votes":0,"percent":0.0},{"id":0,"number":"26","name":"| Left-Wing Alliance","color":"#92864b","votes":1,"percent":0.233},{"id":0,"number":"16","name":"| Change Georgia","color":"#b4ac45","votes":1,"percent":0.233},{"id":0,"number":"21","name":"| Tribune","color":"#f9395a","votes":2,"percent":0.465},{"id":0,"number":"23","name":"| Chven","color":"#47752b","votes":0,"percent":0.0},{"id":0,"number":"3","name":"| The Party of Georgian Unity and Development","color":"#86b5ba","votes":1,"percent":0.233},{"id":0,"number":"27","name":"| Unity of Georgian","color":"#065fc1","votes":1,"percent":0.233},{"id":0,"number":"41","name":"| Georgian Dream","color":"#14477e","votes":256,"percent":59.535},{"id":0,"number":"5","name":"| Unity-National Movement","color":"#e72727","votes":41,"percent":9.535},{"id":0,"number":"36","name":"| Girchi","color":"#386a29","votes":6,"percent":1.395},{"id":0,"number":"9","name":"| Strong Georgia - Lelo, For People, For Liberty!","color":"#d5c907","votes":39,"percent":9.07},{"id":0,"number":"6","name":"| European Democrats","color":"#bbabdc","votes":3,"percent":0.698},{"id":0,"number":"8","name":"| Alliance of Patriots of Georgia","color":"#5848d2","votes":10,"percent":2.326},{"id":0,"number":"4","name":"| Coalition for Changes Gvaramia Melia Girchi Droa","color":"#bcca7a","votes":47,"percent":10.93}],"alias":"00.66.08","number":"08","name":null,"canceled":false,"info":null,"protId":"5fd6ad37-e9b7-45aa-962a-b736edbcfd6b"},{"subjects":[{"id":0,"number":"17","name":"| Sakartvelo","color":"#c24d1b","votes":0,"percent":0.0},{"id":0,"number":"10","name":"| Georgian Labour Party","color":"#292727","votes":1,"percent":0.351},{"id":0,"number":"25","name":"| Gakharia for Georgia","color":"#98ccd2","votes":15,"percent":5.263},{"id":0,"number":"12","name":"| Our United Georgia","color":"#0e2a52","votes":1,"percent":0.351},{"id":0,"number":"20","name":"| Free Georgia","color":"#a90f49","votes":0,"percent":0.0},{"id":0,"number":"26","name":"| Left-Wing Alliance","color":"#92864b","votes":0,"percent":0.0},{"id":0,"number":"16","name":"| Change Georgia","color":"#b4ac45","votes":5,"percent":1.754},{"id":0,"number":"21","name":"| Tribune","color":"#f9395a","votes":1,"percent":0.351},{"id":0,"number":"23","name":"| Chven","color":"#47752b","votes":0,"percent":0.0},{"id":0,"number":"3","name":"| The Party of Georgian Unity and Development","color":"#86b5ba","votes":1,"percent":0.351},{"id":0,"number":"27","name":"| Unity of Georgian","color":"#065fc1","votes":1,"percent":0.351},{"id":0,"number":"41","name":"| Georgian Dream","color":"#14477e","votes":188,"percent":65.965},{"id":0,"number":"5","name":"| Unity-National Movement","color":"#e72727","votes":24,"percent":8.421},{"id":0,"number":"36","name":"| Girchi","color":"#386a29","votes":4,"percent":1.404},{"id":0,"number":"9","name":"| Strong Georgia - Lelo, For People, For Liberty!","color":"#d5c907","votes":17,"percent":5.965},{"id":0,"number":"6","name":"| European Democrats","color":"#bbabdc","votes":0,"percent":0.0},{"id":0,"number":"8","name":"| Alliance of Patriots of Georgia","color":"#5848d2","votes":1,"percent":0.351},{"id":0,"number":"4","name":"| Coalition for Changes Gvaramia Melia Girchi Droa","color":"#bcca7a","votes":26,"percent":9.123}],"alias":"00.66.09","number":"09","name":null,"canceled":false,"info":null,"protId":"517ee216-2e27-431e-a444-6f1fc89ac119"},{"subjects":[{"id":0,"number":"17","name":"| Sakartvelo","color":"#c24d1b","votes":0,"percent":0.0},{"id":0,"number":"10","name":"| Georgian Labour Party","color":"#292727","votes":1,"percent":0.199},{"id":0,"number":"25","name":"| Gakharia for Georgia","color":"#98ccd2","votes":9,"percent":1.789},{"id":0,"number":"12","name":"| Our United Georgia","color":"#0e2a52","votes":0,"percent":0.0},{"id":0,"number":"20","name":"| Free Georgia","color":"#a90f49","votes":0,"percent":0.0},{"id":0,"number":"26","name":"| Left-Wing Alliance","color":"#92864b","votes":0,"percent":0.0},{"id":0,"number":"16","name":"| Change Georgia","color":"#b4ac45","votes":0,"percent":0.0},{"id":0,"number":"21","name":"| Tribune","color":"#f9395a","votes":1,"percent":0.199},{"id":0,"number":"23","name":"| Chven","color":"#47752b","votes":0,"percent":0.0},{"id":0,"number":"3","name":"| The Party of Georgian Unity and Development","color":"#86b5ba","votes":1,"percent":0.199},{"id":0,"number":"27","name":"| Unity of Georgian","color":"#065fc1","votes":1,"percent":0.199},{"id":0,"number":"41","name":"| Georgian Dream","color":"#14477e","votes":283,"percent":56.262},{"id":0,"number":"5","name":"| Unity-National Movement","color":"#e72727","votes":91,"percent":18.091},{"id":0,"number":"36","name":"| Girchi","color":"#386a29","votes":2,"percent":0.398},{"id":0,"number":"9","name":"| Strong Georgia - Lelo, For People, For Liberty!","color":"#d5c907","votes":24,"percent":4.771},{"id":0,"number":"6","name":"| European Democrats","color":"#bbabdc","votes":2,"percent":0.398},{"id":0,"number":"8","name":"| Alliance of Patriots of Georgia","color":"#5848d2","votes":8,"percent":1.59},{"id":0,"number":"4","name":"| Coalition for Changes Gvaramia Melia Girchi Droa","color":"#bcca7a","votes":80,"percent":15.905}],"alias":"00.66.10","number":"10","name":null,"canceled":false,"info":null,"protId":"29d1c114-c9e4-4fca-bbba-63aca63390c2"},{"subjects":[{"id":0,"number":"17","name":"| Sakartvelo","color":"#c24d1b","votes":1,"percent":0.086},{"id":0,"number":"10","name":"| Georgian Labour Party","color":"#292727","votes":4,"percent":0.345},{"id":0,"number":"25","name":"| Gakharia for Georgia","color":"#98ccd2","votes":68,"percent":5.857},{"id":0,"number":"12","name":"| Our United Georgia","color":"#0e2a52","votes":1,"percent":0.086},{"id":0,"number":"20","name":"| Free Georgia","color":"#a90f49","votes":1,"percent":0.086},{"id":0,"number":"26","name":"| Left-Wing Alliance","color":"#92864b","votes":1,"percent":0.086},{"id":0,"number":"16","name":"| Change Georgia","color":"#b4ac45","votes":4,"percent":0.345},{"id":0,"number":"21","name":"| Tribune","color":"#f9395a","votes":2,"percent":0.172},{"id":0,"number":"23","name":"| Chven","color":"#47752b","votes":1,"percent":0.086},{"id":0,"number":"3","name":"| The Party of Georgian Unity and Development","color":"#86b5ba","votes":3,"percent":0.258},{"id":0,"number":"27","name":"| Unity of Georgian","color":"#065fc1","votes":5,"percent":0.431},{"id":0,"number":"41","name":"| Georgian Dream","color":"#14477e","votes":675,"percent":58.14},{"id":0,"number":"5","name":"| Unity-National Movement","color":"#e72727","votes":165,"percent":14.212},{"id":0,"number":"36","name":"| Girchi","color":"#386a29","votes":19,"percent":1.637},{"id":0,"number":"9","name":"| Strong Georgia - Lelo, For People, For Liberty!","color":"#d5c907","votes":56,"percent":4.823},{"id":0,"number":"6","name":"| European Democrats","color":"#bbabdc","votes":6,"percent":0.517},{"id":0,"number":"8","name":"| Alliance of Patriots of Georgia","color":"#5848d2","votes":21,"percent":1.809},{"id":0,"number":"4","name":"| Coalition for Changes Gvaramia Melia Girchi Droa","color":"#bcca7a","votes":128,"percent":11.025}],"alias":"00.66.11","number":"11","name":null,"canceled":false,"info":null,"protId":"186fdccb-e838-4d28-8e22-89b6fd54fd1b"},{"subjects":[{"id":0,"number":"17","name":"| Sakartvelo","color":"#c24d1b","votes":0,"percent":0.0},{"id":0,"number":"10","name":"| Georgian Labour Party","color":"#292727","votes":0,"percent":0.0},{"id":0,"number":"25","name":"| Gakharia for Georgia","color":"#98ccd2","votes":14,"percent":3.341},{"id":0,"number":"12","name":"| Our United Georgia","color":"#0e2a52","votes":0,"percent":0.0},{"id":0,"number":"20","name":"| Free Georgia","color":"#a90f49","votes":1,"percent":0.239},{"id":0,"number":"26","name":"| Left-Wing Alliance","color":"#92864b","votes":2,"percent":0.477},{"id":0,"number":"16","name":"| Change Georgia","color":"#b4ac45","votes":1,"percent":0.239},{"id":0,"number":"21","name":"| Tribune","color":"#f9395a","votes":1,"percent":0.239},{"id":0,"number":"23","name":"| Chven","color":"#47752b","votes":0,"percent":0.0},{"id":0,"number":"3","name":"| The Party of Georgian Unity and Development","color":"#86b5ba","votes":1,"percent":0.239},{"id":0,"number":"27","name":"| Unity of Georgian","color":"#065fc1","votes":2,"percent":0.477},{"id":0,"number":"41","name":"| Georgian Dream","color":"#14477e","votes":285,"percent":68.019},{"id":0,"number":"5","name":"| Unity-National Movement","color":"#e72727","votes":38,"percent":9.069},{"id":0,"number":"36","name":"| Girchi","color":"#386a29","votes":8,"percent":1.909},{"id":0,"number":"9","name":"| Strong Georgia - Lelo, For People, For Liberty!","color":"#d5c907","votes":23,"percent":5.489},{"id":0,"number":"6","name":"| European Democrats","color":"#bbabdc","votes":1,"percent":0.239},{"id":0,"number":"8","name":"| Alliance of Patriots of Georgia","color":"#5848d2","votes":6,"percent":1.432},{"id":0,"number":"4","name":"| Coalition for Changes Gvaramia Melia Girchi Droa","color":"#bcca7a","votes":36,"percent":8.592}],"alias":"00.66.12","number":"12","name":null,"canceled":false,"info":null,"protId":"ca6a1dc5-2efa-4a37-aae8-590ddf17aaea"},{"subjects":[{"id":0,"number":"17","name":"| Sakartvelo","color":"#c24d1b","votes":0,"percent":0.0},{"id":0,"number":"10","name":"| Georgian Labour Party","color":"#292727","votes":3,"percent":0.326},{"id":0,"number":"25","name":"| Gakharia for Georgia","color":"#98ccd2","votes":59,"percent":6.42},{"id":0,"number":"12","name":"| Our United Georgia","color":"#0e2a52","votes":0,"percent":0.0},{"id":0,"number":"20","name":"| Free Georgia","color":"#a90f49","votes":1,"percent":0.109},{"id":0,"number":"26","name":"| Left-Wing Alliance","color":"#92864b","votes":1,"percent":0.109},{"id":0,"number":"16","name":"| Change Georgia","color":"#b4ac45","votes":1,"percent":0.109},{"id":0,"number":"21","name":"| Tribune","color":"#f9395a","votes":2,"percent":0.218},{"id":0,"number":"23","name":"| Chven","color":"#47752b","votes":1,"percent":0.109},{"id":0,"number":"3","name":"| The Party of Georgian Unity and Development","color":"#86b5ba","votes":3,"percent":0.326},{"id":0,"number":"27","name":"| Unity of Georgian","color":"#065fc1","votes":3,"percent":0.326},{"id":0,"number":"41","name":"| Georgian Dream","color":"#14477e","votes":540,"percent":58.76},{"id":0,"number":"5","name":"| Unity-National Movement","color":"#e72727","votes":72,"percent":7.835},{"id":0,"number":"36","name":"| Girchi","color":"#386a29","votes":19,"percent":2.067},{"id":0,"number":"9","name":"| Strong Georgia - Lelo, For People, For Liberty!","color":"#d5c907","votes":69,"percent":7.508},{"id":0,"number":"6","name":"| European Democrats","color":"#bbabdc","votes":8,"percent":0.871},{"id":0,"number":"8","name":"| Alliance of Patriots of Georgia","color":"#5848d2","votes":17,"percent":1.85},{"id":0,"number":"4","name":"| Coalition for Changes Gvaramia Melia Girchi Droa","color":"#bcca7a","votes":120,"percent":13.058}],"alias":"00.66.13","number":"13","name":null,"canceled":false,"info":null,"protId":"dc15369e-f438-4a59-96bf-8f4ef3f361a1"},{"subjects":[{"id":0,"number":"17","name":"| Sakartvelo","color":"#c24d1b","votes":2,"percent":0.784},{"id":0,"number":"10","name":"| Georgian Labour Party","color":"#292727","votes":0,"percent":0.0},{"id":0,"number":"25","name":"| Gakharia for Georgia","color":"#98ccd2","votes":8,"percent":3.137},{"id":0,"number":"12","name":"| Our United Georgia","color":"#0e2a52","votes":3,"percent":1.176},{"id":0,"number":"20","name":"| Free Georgia","color":"#a90f49","votes":0,"percent":0.0},{"id":0,"number":"26","name":"| Left-Wing Alliance","color":"#92864b","votes":0,"percent":0.0},{"id":0,"number":"16","name":"| Change Georgia","color":"#b4ac45","votes":0,"percent":0.0},{"id":0,"number":"21","name":"| Tribune","color":"#f9395a","votes":0,"percent":0.0},{"id":0,"number":"23","name":"| Chven","color":"#47752b","votes":0,"percent":0.0},{"id":0,"number":"3","name":"| The Party of Georgian Unity and Development","color":"#86b5ba","votes":0,"percent":0.0},{"id":0,"number":"27","name":"| Unity of Georgian","color":"#065fc1","votes":0,"percent":0.0},{"id":0,"number":"41","name":"| Georgian Dream","color":"#14477e","votes":186,"percent":72.941},{"id":0,"number":"5","name":"| Unity-National Movement","color":"#e72727","votes":25,"percent":9.804},{"id":0,"number":"36","name":"| Girchi","color":"#386a29","votes":1,"percent":0.392},{"id":0,"number":"9","name":"| Strong Georgia - Lelo, For People, For Liberty!","color":"#d5c907","votes":12,"percent":4.706},{"id":0,"number":"6","name":"| European Democrats","color":"#bbabdc","votes":2,"percent":0.784},{"id":0,"number":"8","name":"| Alliance of Patriots of Georgia","color":"#5848d2","votes":6,"percent":2.353},{"id":0,"number":"4","name":"| Coalition for Changes Gvaramia Melia Girchi Droa","color":"#bcca7a","votes":10,"percent":3.922}],"alias":"00.66.14","number":"14","name":null,"canceled":false,"info":null,"protId":"4e447d09-ef97-419c-aa23-e4dc3b3388f5"},{"subjects":[{"id":0,"number":"17","name":"| Sakartvelo","color":"#c24d1b","votes":2,"percent":0.176},{"id":0,"number":"10","name":"| Georgian Labour Party","color":"#292727","votes":6,"percent":0.527},{"id":0,"number":"25","name":"| Gakharia for Georgia","color":"#98ccd2","votes":67,"percent":5.888},{"id":0,"number":"12","name":"| Our United Georgia","color":"#0e2a52","votes":1,"percent":0.088},{"id":0,"number":"20","name":"| Free Georgia","color":"#a90f49","votes":2,"percent":0.176},{"id":0,"number":"26","name":"| Left-Wing Alliance","color":"#92864b","votes":1,"percent":0.088},{"id":0,"number":"16","name":"| Change Georgia","color":"#b4ac45","votes":3,"percent":0.264},{"id":0,"number":"21","name":"| Tribune","color":"#f9395a","votes":2,"percent":0.176},{"id":0,"number":"23","name":"| Chven","color":"#47752b","votes":3,"percent":0.264},{"id":0,"number":"3","name":"| The Party of Georgian Unity and Development","color":"#86b5ba","votes":2,"percent":0.176},{"id":0,"number":"27","name":"| Unity of Georgian","color":"#065fc1","votes":5,"percent":0.439},{"id":0,"number":"41","name":"| Georgian Dream","color":"#14477e","votes":598,"percent":52.548},{"id":0,"number":"5","name":"| Unity-National Movement","color":"#e72727","votes":190,"percent":16.696},{"id":0,"number":"36","name":"| Girchi","color":"#386a29","votes":13,"percent":1.142},{"id":0,"number":"9","name":"| Strong Georgia - Lelo, For People, For Liberty!","color":"#d5c907","votes":54,"percent":4.745},{"id":0,"number":"6","name":"| European Democrats","color":"#bbabdc","votes":12,"percent":1.054},{"id":0,"number":"8","name":"| Alliance of Patriots of Georgia","color":"#5848d2","votes":17,"percent":1.494},{"id":0,"number":"4","name":"| Coalition for Changes Gvaramia Melia Girchi Droa","color":"#bcca7a","votes":160,"percent":14.06}],"alias":"00.66.15","number":"15","name":null,"canceled":false,"info":null,"protId":"806896e6-af34-4bd9-8b1e-e2a4ce91f013"},{"subjects":[{"id":0,"number":"17","name":"| Sakartvelo","color":"#c24d1b","votes":0,"percent":0.0},{"id":0,"number":"10","name":"| Georgian Labour Party","color":"#292727","votes":0,"percent":0.0},{"id":0,"number":"25","name":"| Gakharia for Georgia","color":"#98ccd2","votes":19,"percent":8.482},{"id":0,"number":"12","name":"| Our United Georgia","color":"#0e2a52","votes":1,"percent":0.446},{"id":0,"number":"20","name":"| Free Georgia","color":"#a90f49","votes":1,"percent":0.446},{"id":0,"number":"26","name":"| Left-Wing Alliance","color":"#92864b","votes":0,"percent":0.0},{"id":0,"number":"16","name":"| Change Georgia","color":"#b4ac45","votes":0,"percent":0.0},{"id":0,"number":"21","name":"| Tribune","color":"#f9395a","votes":1,"percent":0.446},{"id":0,"number":"23","name":"| Chven","color":"#47752b","votes":0,"percent":0.0},{"id":0,"number":"3","name":"| The Party of Georgian Unity and Development","color":"#86b5ba","votes":0,"percent":0.0},{"id":0,"number":"27","name":"| Unity of Georgian","color":"#065fc1","votes":1,"percent":0.446},{"id":0,"number":"41","name":"| Georgian Dream","color":"#14477e","votes":107,"percent":47.768},{"id":0,"number":"5","name":"| Unity-National Movement","color":"#e72727","votes":34,"percent":15.179},{"id":0,"number":"36","name":"| Girchi","color":"#386a29","votes":0,"percent":0.0},{"id":0,"number":"9","name":"| Strong Georgia - Lelo, For People, For Liberty!","color":"#d5c907","votes":19,"percent":8.482},{"id":0,"number":"6","name":"| European Democrats","color":"#bbabdc","votes":2,"percent":0.893},{"id":0,"number":"8","name":"| Alliance of Patriots of Georgia","color":"#5848d2","votes":0,"percent":0.0},{"id":0,"number":"4","name":"| Coalition for Changes Gvaramia Melia Girchi Droa","color":"#bcca7a","votes":39,"percent":17.411}],"alias":"00.66.16","number":"16","name":null,"canceled":false,"info":null,"protId":"7e865096-a63e-446e-a36e-5ae15356625b"},{"subjects":[{"id":0,"number":"17","name":"| Sakartvelo","color":"#c24d1b","votes":1,"percent":0.316},{"id":0,"number":"10","name":"| Georgian Labour Party","color":"#292727","votes":0,"percent":0.0},{"id":0,"number":"25","name":"| Gakharia for Georgia","color":"#98ccd2","votes":7,"percent":2.215},{"id":0,"number":"12","name":"| Our United Georgia","color":"#0e2a52","votes":0,"percent":0.0},{"id":0,"number":"20","name":"| Free Georgia","color":"#a90f49","votes":0,"percent":0.0},{"id":0,"number":"26","name":"| Left-Wing Alliance","color":"#92864b","votes":0,"percent":0.0},{"id":0,"number":"16","name":"| Change Georgia","color":"#b4ac45","votes":0,"percent":0.0},{"id":0,"number":"21","name":"| Tribune","color":"#f9395a","votes":1,"percent":0.316},{"id":0,"number":"23","name":"| Chven","color":"#47752b","votes":1,"percent":0.316},{"id":0,"number":"3","name":"| The Party of Georgian Unity and Development","color":"#86b5ba","votes":0,"percent":0.0},{"id":0,"number":"27","name":"| Unity of Georgian","color":"#065fc1","votes":0,"percent":0.0},{"id":0,"number":"41","name":"| Georgian Dream","color":"#14477e","votes":240,"percent":75.949},{"id":0,"number":"5","name":"| Unity-National Movement","color":"#e72727","votes":25,"percent":7.911},{"id":0,"number":"36","name":"| Girchi","color":"#386a29","votes":1,"percent":0.316},{"id":0,"number":"9","name":"| Strong Georgia - Lelo, For People, For Liberty!","color":"#d5c907","votes":8,"percent":2.532},{"id":0,"number":"6","name":"| European Democrats","color":"#bbabdc","votes":0,"percent":0.0},{"id":0,"number":"8","name":"| Alliance of Patriots of Georgia","color":"#5848d2","votes":2,"percent":0.633},{"id":0,"number":"4","name":"| Coalition for Changes Gvaramia Melia Girchi Droa","color":"#bcca7a","votes":30,"percent":9.494}],"alias":"00.66.17","number":"17","name":null,"canceled":false,"info":null,"protId":"5c16a73d-031d-41af-be17-0589478f35b8"},{"subjects":[{"id":0,"number":"17","name":"| Sakartvelo","color":"#c24d1b","votes":0,"percent":0.0},{"id":0,"number":"10","name":"| Georgian Labour Party","color":"#292727","votes":3,"percent":0.704},{"id":0,"number":"25","name":"| Gakharia for Georgia","color":"#98ccd2","votes":13,"percent":3.052},{"id":0,"number":"12","name":"| Our United Georgia","color":"#0e2a52","votes":0,"percent":0.0},{"id":0,"number":"20","name":"| Free Georgia","color":"#a90f49","votes":0,"percent":0.0},{"id":0,"number":"26","name":"| Left-Wing Alliance","color":"#92864b","votes":0,"percent":0.0},{"id":0,"number":"16","name":"| Change Georgia","color":"#b4ac45","votes":0,"percent":0.0},{"id":0,"number":"21","name":"| Tribune","color":"#f9395a","votes":0,"percent":0.0},{"id":0,"number":"23","name":"| Chven","color":"#47752b","votes":0,"percent":0.0},{"id":0,"number":"3","name":"| The Party of Georgian Unity and Development","color":"#86b5ba","votes":2,"percent":0.469},{"id":0,"number":"27","name":"| Unity of Georgian","color":"#065fc1","votes":0,"percent":0.0},{"id":0,"number":"41","name":"| Georgian Dream","color":"#14477e","votes":230,"percent":53.991},{"id":0,"number":"5","name":"| Unity-National Movement","color":"#e72727","votes":29,"percent":6.808},{"id":0,"number":"36","name":"| Girchi","color":"#386a29","votes":6,"percent":1.408},{"id":0,"number":"9","name":"| Strong Georgia - Lelo, For People, For Liberty!","color":"#d5c907","votes":15,"percent":3.521},{"id":0,"number":"6","name":"| European Democrats","color":"#bbabdc","votes":7,"percent":1.643},{"id":0,"number":"8","name":"| Alliance of Patriots of Georgia","color":"#5848d2","votes":1,"percent":0.235},{"id":0,"number":"4","name":"| Coalition for Changes Gvaramia Melia Girchi Droa","color":"#bcca7a","votes":120,"percent":28.169}],"alias":"00.66.18","number":"18","name":null,"canceled":false,"info":null,"protId":"33281b63-1e4e-4d9d-97fa-04c708d2bae0"},{"subjects":[{"id":0,"number":"17","name":"| Sakartvelo","color":"#c24d1b","votes":1,"percent":0.125},{"id":0,"number":"10","name":"| Georgian Labour Party","color":"#292727","votes":1,"percent":0.125},{"id":0,"number":"25","name":"| Gakharia for Georgia","color":"#98ccd2","votes":41,"percent":5.144},{"id":0,"number":"12","name":"| Our United Georgia","color":"#0e2a52","votes":0,"percent":0.0},{"id":0,"number":"20","name":"| Free Georgia","color":"#a90f49","votes":0,"percent":0.0},{"id":0,"number":"26","name":"| Left-Wing Alliance","color":"#92864b","votes":0,"percent":0.0},{"id":0,"number":"16","name":"| Change Georgia","color":"#b4ac45","votes":2,"percent":0.251},{"id":0,"number":"21","name":"| Tribune","color":"#f9395a","votes":1,"percent":0.125},{"id":0,"number":"23","name":"| Chven","color":"#47752b","votes":0,"percent":0.0},{"id":0,"number":"3","name":"| The Party of Georgian Unity and Development","color":"#86b5ba","votes":0,"percent":0.0},{"id":0,"number":"27","name":"| Unity of Georgian","color":"#065fc1","votes":1,"percent":0.125},{"id":0,"number":"41","name":"| Georgian Dream","color":"#14477e","votes":488,"percent":61.23},{"id":0,"number":"5","name":"| Unity-National Movement","color":"#e72727","votes":88,"percent":11.041},{"id":0,"number":"36","name":"| Girchi","color":"#386a29","votes":5,"percent":0.627},{"id":0,"number":"9","name":"| Strong Georgia - Lelo, For People, For Liberty!","color":"#d5c907","votes":68,"percent":8.532},{"id":0,"number":"6","name":"| European Democrats","color":"#bbabdc","votes":4,"percent":0.502},{"id":0,"number":"8","name":"| Alliance of Patriots of Georgia","color":"#5848d2","votes":16,"percent":2.008},{"id":0,"number":"4","name":"| Coalition for Changes Gvaramia Melia Girchi Droa","color":"#bcca7a","votes":81,"percent":10.163}],"alias":"00.66.19","number":"19","name":null,"canceled":false,"info":null,"protId":"c00d650e-ffee-49d4-abec-a0b89f4bc4d5"},{"subjects":[{"id":0,"number":"17","name":"| Sakartvelo","color":"#c24d1b","votes":0,"percent":0.0},{"id":0,"number":"10","name":"| Georgian Labour Party","color":"#292727","votes":6,"percent":1.714},{"id":0,"number":"25","name":"| Gakharia for Georgia","color":"#98ccd2","votes":12,"percent":3.429},{"id":0,"number":"12","name":"| Our United Georgia","color":"#0e2a52","votes":0,"percent":0.0},{"id":0,"number":"20","name":"| Free Georgia","color":"#a90f49","votes":1,"percent":0.286},{"id":0,"number":"26","name":"| Left-Wing Alliance","color":"#92864b","votes":1,"percent":0.286},{"id":0,"number":"16","name":"| Change Georgia","color":"#b4ac45","votes":4,"percent":1.143},{"id":0,"number":"21","name":"| Tribune","color":"#f9395a","votes":1,"percent":0.286},{"id":0,"number":"23","name":"| Chven","color":"#47752b","votes":0,"percent":0.0},{"id":0,"number":"3","name":"| The Party of Georgian Unity and Development","color":"#86b5ba","votes":0,"percent":0.0},{"id":0,"number":"27","name":"| Unity of Georgian","color":"#065fc1","votes":1,"percent":0.286},{"id":0,"number":"41","name":"| Georgian Dream","color":"#14477e","votes":211,"percent":60.286},{"id":0,"number":"5","name":"| Unity-National Movement","color":"#e72727","votes":37,"percent":10.571},{"id":0,"number":"36","name":"| Girchi","color":"#386a29","votes":3,"percent":0.857},{"id":0,"number":"9","name":"| Strong Georgia - Lelo, For People, For Liberty!","color":"#d5c907","votes":24,"percent":6.857},{"id":0,"number":"6","name":"| European Democrats","color":"#bbabdc","votes":1,"percent":0.286},{"id":0,"number":"8","name":"| Alliance of Patriots of Georgia","color":"#5848d2","votes":4,"percent":1.143},{"id":0,"number":"4","name":"| Coalition for Changes Gvaramia Melia Girchi Droa","color":"#bcca7a","votes":44,"percent":12.571}],"alias":"00.66.20","number":"20","name":null,"canceled":false,"info":null,"protId":"45f3047f-3f26-4849-bb75-5c4ed6dcdfc6"},{"subjects":[{"id":0,"number":"17","name":"| Sakartvelo","color":"#c24d1b","votes":2,"percent":0.22},{"id":0,"number":"10","name":"| Georgian Labour Party","color":"#292727","votes":1,"percent":0.11},{"id":0,"number":"25","name":"| Gakharia for Georgia","color":"#98ccd2","votes":53,"percent":5.831},{"id":0,"number":"12","name":"| Our United Georgia","color":"#0e2a52","votes":1,"percent":0.11},{"id":0,"number":"20","name":"| Free Georgia","color":"#a90f49","votes":2,"percent":0.22},{"id":0,"number":"26","name":"| Left-Wing Alliance","color":"#92864b","votes":5,"percent":0.55},{"id":0,"number":"16","name":"| Change Georgia","color":"#b4ac45","votes":6,"percent":0.66},{"id":0,"number":"21","name":"| Tribune","color":"#f9395a","votes":1,"percent":0.11},{"id":0,"number":"23","name":"| Chven","color":"#47752b","votes":0,"percent":0.0},{"id":0,"number":"3","name":"| The Party of Georgian Unity and Development","color":"#86b5ba","votes":3,"percent":0.33},{"id":0,"number":"27","name":"| Unity of Georgian","color":"#065fc1","votes":0,"percent":0.0},{"id":0,"number":"41","name":"| Georgian Dream","color":"#14477e","votes":532,"percent":58.526},{"id":0,"number":"5","name":"| Unity-National Movement","color":"#e72727","votes":108,"percent":11.881},{"id":0,"number":"36","name":"| Girchi","color":"#386a29","votes":10,"percent":1.1},{"id":0,"number":"9","name":"| Strong Georgia - Lelo, For People, For Liberty!","color":"#d5c907","votes":60,"percent":6.601},{"id":0,"number":"6","name":"| European Democrats","color":"#bbabdc","votes":12,"percent":1.32},{"id":0,"number":"8","name":"| Alliance of Patriots of Georgia","color":"#5848d2","votes":12,"percent":1.32},{"id":0,"number":"4","name":"| Coalition for Changes Gvaramia Melia Girchi Droa","color":"#bcca7a","votes":101,"percent":11.111}],"alias":"00.66.21","number":"21","name":null,"canceled":false,"info":null,"protId":"6e15dbc6-1ea6-4b21-b149-68316fcf07b2"},{"subjects":[{"id":0,"number":"17","name":"| Sakartvelo","color":"#c24d1b","votes":0,"percent":0.0},{"id":0,"number":"10","name":"| Georgian Labour Party","color":"#292727","votes":0,"percent":0.0},{"id":0,"number":"25","name":"| Gakharia for Georgia","color":"#98ccd2","votes":23,"percent":13.772},{"id":0,"number":"12","name":"| Our United Georgia","color":"#0e2a52","votes":0,"percent":0.0},{"id":0,"number":"20","name":"| Free Georgia","color":"#a90f49","votes":0,"percent":0.0},{"id":0,"number":"26","name":"| Left-Wing Alliance","color":"#92864b","votes":0,"percent":0.0},{"id":0,"number":"16","name":"| Change Georgia","color":"#b4ac45","votes":0,"percent":0.0},{"id":0,"number":"21","name":"| Tribune","color":"#f9395a","votes":0,"percent":0.0},{"id":0,"number":"23","name":"| Chven","color":"#47752b","votes":0,"percent":0.0},{"id":0,"number":"3","name":"| The Party of Georgian Unity and Development","color":"#86b5ba","votes":0,"percent":0.0},{"id":0,"number":"27","name":"| Unity of Georgian","color":"#065fc1","votes":0,"percent":0.0},{"id":0,"number":"41","name":"| Georgian Dream","color":"#14477e","votes":105,"percent":62.874},{"id":0,"number":"5","name":"| Unity-National Movement","color":"#e72727","votes":17,"percent":10.18},{"id":0,"number":"36","name":"| Girchi","color":"#386a29","votes":1,"percent":0.599},{"id":0,"number":"9","name":"| Strong Georgia - Lelo, For People, For Liberty!","color":"#d5c907","votes":12,"percent":7.186},{"id":0,"number":"6","name":"| European Democrats","color":"#bbabdc","votes":0,"percent":0.0},{"id":0,"number":"8","name":"| Alliance of Patriots of Georgia","color":"#5848d2","votes":0,"percent":0.0},{"id":0,"number":"4","name":"| Coalition for Changes Gvaramia Melia Girchi Droa","color":"#bcca7a","votes":9,"percent":5.389}],"alias":"00.66.22","number":"22","name":null,"canceled":false,"info":null,"protId":"1fe6c649-09c7-403a-bb33-2a9ab957a262"},{"subjects":[{"id":0,"number":"17","name":"| Sakartvelo","color":"#c24d1b","votes":1,"percent":0.147},{"id":0,"number":"10","name":"| Georgian Labour Party","color":"#292727","votes":1,"percent":0.147},{"id":0,"number":"25","name":"| Gakharia for Georgia","color":"#98ccd2","votes":28,"percent":4.106},{"id":0,"number":"12","name":"| Our United Georgia","color":"#0e2a52","votes":0,"percent":0.0},{"id":0,"number":"20","name":"| Free Georgia","color":"#a90f49","votes":2,"percent":0.293},{"id":0,"number":"26","name":"| Left-Wing Alliance","color":"#92864b","votes":0,"percent":0.0},{"id":0,"number":"16","name":"| Change Georgia","color":"#b4ac45","votes":2,"percent":0.293},{"id":0,"number":"21","name":"| Tribune","color":"#f9395a","votes":0,"percent":0.0},{"id":0,"number":"23","name":"| Chven","color":"#47752b","votes":0,"percent":0.0},{"id":0,"number":"3","name":"| The Party of Georgian Unity and Development","color":"#86b5ba","votes":1,"percent":0.147},{"id":0,"number":"27","name":"| Unity of Georgian","color":"#065fc1","votes":1,"percent":0.147},{"id":0,"number":"41","name":"| Georgian Dream","color":"#14477e","votes":380,"percent":55.718},{"id":0,"number":"5","name":"| Unity-National Movement","color":"#e72727","votes":85,"percent":12.463},{"id":0,"number":"36","name":"| Girchi","color":"#386a29","votes":12,"percent":1.76},{"id":0,"number":"9","name":"| Strong Georgia - Lelo, For People, For Liberty!","color":"#d5c907","votes":82,"percent":12.023},{"id":0,"number":"6","name":"| European Democrats","color":"#bbabdc","votes":4,"percent":0.587},{"id":0,"number":"8","name":"| Alliance of Patriots of Georgia","color":"#5848d2","votes":9,"percent":1.32},{"id":0,"number":"4","name":"| Coalition for Changes Gvaramia Melia Girchi Droa","color":"#bcca7a","votes":74,"percent":10.85}],"alias":"00.66.23","number":"23","name":null,"canceled":false,"info":null,"protId":"485439d9-982f-4cc1-95aa-cf27a5f0bf9a"},{"subjects":[{"id":0,"number":"17","name":"| Sakartvelo","color":"#c24d1b","votes":0,"percent":0.0},{"id":0,"number":"10","name":"| Georgian Labour Party","color":"#292727","votes":0,"percent":0.0},{"id":0,"number":"25","name":"| Gakharia for Georgia","color":"#98ccd2","votes":8,"percent":2.073},{"id":0,"number":"12","name":"| Our United Georgia","color":"#0e2a52","votes":0,"percent":0.0},{"id":0,"number":"20","name":"| Free Georgia","color":"#a90f49","votes":0,"percent":0.0},{"id":0,"number":"26","name":"| Left-Wing Alliance","color":"#92864b","votes":2,"percent":0.518},{"id":0,"number":"16","name":"| Change Georgia","color":"#b4ac45","votes":0,"percent":0.0},{"id":0,"number":"21","name":"| Tribune","color":"#f9395a","votes":1,"percent":0.259},{"id":0,"number":"23","name":"| Chven","color":"#47752b","votes":0,"percent":0.0},{"id":0,"number":"3","name":"| The Party of Georgian Unity and Development","color":"#86b5ba","votes":0,"percent":0.0},{"id":0,"number":"27","name":"| Unity of Georgian","color":"#065fc1","votes":0,"percent":0.0},{"id":0,"number":"41","name":"| Georgian Dream","color":"#14477e","votes":204,"percent":52.85},{"id":0,"number":"5","name":"| Unity-National Movement","color":"#e72727","votes":49,"percent":12.694},{"id":0,"number":"36","name":"| Girchi","color":"#386a29","votes":2,"percent":0.518},{"id":0,"number":"9","name":"| Strong Georgia - Lelo, For People, For Liberty!","color":"#d5c907","votes":21,"percent":5.44},{"id":0,"number":"6","name":"| European Democrats","color":"#bbabdc","votes":4,"percent":1.036},{"id":0,"number":"8","name":"| Alliance of Patriots of Georgia","color":"#5848d2","votes":6,"percent":1.554},{"id":0,"number":"4","name":"| Coalition for Changes Gvaramia Melia Girchi Droa","color":"#bcca7a","votes":89,"percent":23.057}],"alias":"00.66.24","number":"24","name":null,"canceled":false,"info":null,"protId":"484ef287-07e1-4a41-bba1-bf906cdd5e24"}]}